html_to_adf.py
html_to_adf-0.1.0.dist-info/licenses/LICENSE
html_to_adf-0.1.0.dist-info/METADATA
html_to_adf-0.1.0.dist-info/WHEEL
html_to_adf-0.1.0.dist-info/top_level.txt
html_to_adf-0.1.0.dist-info/RECORD
