Metadata-Version: 2.4
Name: html-to-adf
Version: 0.1.0
Summary: Convert HTML to Atlassian Document Format (ADF) for Jira and Confluence.
Author-email: Avery Tomlin <actesbusiness@gmail.com>
License: MIT
Project-URL: Homepage, https://github.com/actes2/html-to-adf
Project-URL: Documentation, https://github.com/actes2/html-to-adf#readme
Project-URL: Issues, https://github.com/actes2/html-to-adf/issues
Keywords: atlassian,jira,adf,html,converter
Requires-Python: >=3.9
License-File: LICENSE
Requires-Dist: beautifulsoup4
Dynamic: license-file
